slxpy/__init__.py
slxpy/backend/__init__.py
slxpy/backend/filter.py
slxpy/backend/renderer.py
slxpy/cli/__init__.py
slxpy/cli/clean.py
slxpy/cli/conda.py
slxpy/cli/generate.py
slxpy/cli/init.py
slxpy/cli/multi_build.py
slxpy/cli/pack.py
slxpy/cli/utils.py
slxpy/common/__init__.py
slxpy/common/constants.py
slxpy/common/context.py
slxpy/common/enum.py
slxpy/common/env_config.py
slxpy/common/formatter.py
slxpy/common/fs.py
slxpy/common/init_config.py
slxpy/common/jinja.py
slxpy/common/mapping.py
slxpy/common/model_config.py
slxpy/common/space_config.py
slxpy/common/tsort.py
slxpy/frontend/__init__.py
slxpy/frontend/frontend.py
slxpy/frontend/init.py
slxpy/include/bind.h
slxpy/include/common.h
slxpy/include/complex.h
slxpy/include/data.h
slxpy/include/env.h
slxpy/include/simulink_builtin.h
slxpy/include/third-party/README.md
slxpy/include/third-party/fmt/args.h
slxpy/include/third-party/fmt/chrono.h
slxpy/include/third-party/fmt/color.h
slxpy/include/third-party/fmt/compile.h
slxpy/include/third-party/fmt/core.h
slxpy/include/third-party/fmt/format-inl.h
slxpy/include/third-party/fmt/format.h
slxpy/include/third-party/fmt/os.h
slxpy/include/third-party/fmt/ostream.h
slxpy/include/third-party/fmt/printf.h
slxpy/include/third-party/fmt/ranges.h
slxpy/include/third-party/fmt/std.h
slxpy/include/third-party/fmt/xchar.h
slxpy/include/third-party/nlohmann/adl_serializer.hpp
slxpy/include/third-party/nlohmann/byte_container_with_subtype.hpp
slxpy/include/third-party/nlohmann/json.hpp
slxpy/include/third-party/nlohmann/json_fwd.hpp
slxpy/include/third-party/nlohmann/ordered_map.hpp
slxpy/include/third-party/nlohmann/detail/abi_macros.hpp
slxpy/include/third-party/nlohmann/detail/exceptions.hpp
slxpy/include/third-party/nlohmann/detail/hash.hpp
slxpy/include/third-party/nlohmann/detail/json_pointer.hpp
slxpy/include/third-party/nlohmann/detail/json_ref.hpp
slxpy/include/third-party/nlohmann/detail/macro_scope.hpp
slxpy/include/third-party/nlohmann/detail/macro_unscope.hpp
slxpy_fork-1.6.2.post1.dist-info/LICENSE
slxpy_fork-1.6.2.post1.dist-info/METADATA
slxpy_fork-1.6.2.post1.dist-info/WHEEL
slxpy_fork-1.6.2.post1.dist-info/entry_points.txt
slxpy_fork-1.6.2.post1.dist-info/top_level.txt
slxpy_fork-1.6.2.post1.dist-info/RECORD
